{
  "devices": [      
    {
      "device": {
        "deviceID": "EBB620E023B3FA0A72CAF31B46A21A51213C590E",
        "os": "iOS",
        "name": "iPhone 5",
        "isDesktopBrowser": "false",
        "runNative": "true",
        "runWeb": "true"
      }
    },
    {
      "device": {
        "deviceID": "067C0546439C8F54",
        "os": "Android",
        "name": "Nexus 5",
        "isDesktopBrowser": "false",
        "runNative": "false",
        "runWeb": "true"
      }
    },
    {
      "device": {
        "deviceID": "HT58ZJT00147",
        "os": "Android",
        "name": "Nexus 9 Tablet",
        "isDesktopBrowser": "false",
        "runNative": "false",
        "runWeb": "true"
      }
    },
    {
      "device": {
        "deviceID": "95E0EEA907ECC690914C7ABE68786B3EDE4343DF",
        "os": "iOS",
        "name": "iPadAir2",
        "isDesktopBrowser": "false",
        "runNative": "false",
        "runWeb": "true"
      }
    }
  ]
}